cube/__init__.py
cube/__main__.py
AkshayFirstModule-1.0.1.dist-info/LICENSE
AkshayFirstModule-1.0.1.dist-info/METADATA
AkshayFirstModule-1.0.1.dist-info/WHEEL
AkshayFirstModule-1.0.1.dist-info/entry_points.txt
AkshayFirstModule-1.0.1.dist-info/top_level.txt
AkshayFirstModule-1.0.1.dist-info/RECORD
