Metadata-Version: 2.1
Name: AkshayFirstModule
Version: 1.0.1
Summary: It cubes the number
Home-page: https://github.com/adhomse/AkshayFirstModule
Author: Akshay Dhomse
Author-email: adhomse99@gmail.com
License: MIT
Platform: UNKNOWN
Classifier: License :: OSI Approved :: MIT License
Classifier: Programming Language :: Python :: 3.6
Classifier: Programming Language :: Python :: 3.7
Classifier: Programming Language :: Python :: 3.8
